imagestoanimation/__init__.py
imagestoanimation/requirements.txt
imagestoanimation/script.py
imagestoanimation/settings.conf
imagestoanimation-0.1.9.dist-info/entry_points.txt
imagestoanimation-0.1.9.dist-info/LICENSE
imagestoanimation-0.1.9.dist-info/WHEEL
imagestoanimation-0.1.9.dist-info/METADATA
imagestoanimation-0.1.9.dist-info/RECORD
